fast_gliner-0.1.12.dist-info/METADATA
fast_gliner-0.1.12.dist-info/WHEEL
fast_gliner/__init__.py
fast_gliner/fast_gliner.cpython-39-darwin.so
fast_gliner-0.1.12.dist-info/RECORD
