Metadata-Version: 2.4
Name: fast_gliner
Version: 0.1.12
Classifier: Development Status :: 5 - Production/Stable
Classifier: Intended Audience :: Developers
Classifier: Intended Audience :: Education
Classifier: Intended Audience :: Science/Research
Classifier: License :: OSI Approved :: Apache Software License
Classifier: Operating System :: OS Independent
Classifier: Programming Language :: Python :: 3
Classifier: Programming Language :: Python :: 3.9
Classifier: Programming Language :: Python :: 3.10
Classifier: Programming Language :: Python :: 3.11
Classifier: Programming Language :: Python :: 3.12
Classifier: Programming Language :: Python :: 3.13
Classifier: Programming Language :: Python :: 3 :: Only
Classifier: Topic :: Scientific/Engineering :: Artificial Intelligence
Requires-Dist: huggingface-hub>=0.16.4,<1.0
Provides-Extra: cuda
Summary: Python bindings for gline-rs: Inference Engine for GLiNER Models, written in Rust
Keywords: nlp,ner,named entity recognition,natural language processing,onnx,transformers,rust,pyo3,gliner,span extraction,token classification,zero-shot
Author-email: Tal Almagor <almagoric@gmail.com>
License: Apache
Requires-Python: >=3.9
